ayab/LICENSE.txt
ayab/__init__.py
ayab/ayab.py
ayab/ayab_about.py
ayab/ayab_gui.BASE.ts
ayab/ayab_gui.py
ayab/knit_aware_resize.py
ayab/package_version
ayab/resources_rc.py
ayab/plugins/__init__.py
ayab/plugins/ayab_plugin.yapsy-plugin
ayab/plugins/dummy_plugin.yapsy-plugin
ayab/plugins/knitting_plugin.py
ayab/plugins/ayab_plugin/__init__.py
ayab/plugins/ayab_plugin/ayab_communication.py
ayab/plugins/ayab_plugin/ayab_control.py
ayab/plugins/ayab_plugin/ayab_image.py
ayab/plugins/ayab_plugin/ayab_options.de_DE.qm
ayab/plugins/ayab_plugin/ayab_options.de_DE.ts
ayab/plugins/ayab_plugin/ayab_options.en_US.qm
ayab/plugins/ayab_plugin/ayab_options.en_US.ts
ayab/plugins/ayab_plugin/ayab_options.py
ayab/plugins/ayab_plugin/ayab_options.qm
ayab/plugins/ayab_plugin/firmware_flash.py
ayab/plugins/ayab_plugin/firmware_flash_ui.py
ayab/plugins/ayab_plugin/firmware/avrdude.conf
ayab/plugins/ayab_plugin/firmware/avrdude.exe
ayab/plugins/ayab_plugin/firmware/avrdude_bin
ayab/plugins/ayab_plugin/firmware/avrdude_mac
ayab/plugins/ayab_plugin/firmware/firmware.json
ayab/plugins/ayab_plugin/firmware/libusb0.dll
ayab/plugins/ayab_plugin/firmware/mega2560/hwtest_mega_0-80.hex
ayab/plugins/ayab_plugin/firmware/mega2560/kh910_mega_0-80.hex
ayab/plugins/ayab_plugin/firmware/mega2560/kh910_mega_0-90.hex
ayab/plugins/ayab_plugin/firmware/mega2560/kh930_mega_0-80.hex
ayab/plugins/ayab_plugin/firmware/mega2560/kh930_mega_0-90.hex
ayab/plugins/ayab_plugin/firmware/uno/hwtest_uno_0-80.hex
ayab/plugins/ayab_plugin/firmware/uno/kh910_uno_0-80.hex
ayab/plugins/ayab_plugin/firmware/uno/kh910_uno_0-90.hex
ayab/plugins/ayab_plugin/firmware/uno/kh930_uno_0-80.hex
ayab/plugins/ayab_plugin/firmware/uno/kh930_uno_0-90.hex
ayab/plugins/dummy_knitting_plugin/__init__.py
ayab/plugins/dummy_knitting_plugin/dummy_plugin.py
ayab/tests/test_communication.py
ayab/translations/ayab_gui.de_DE.qm
ayab/translations/ayab_gui.de_DE.ts
ayab/translations/ayab_gui.en_US.qm
ayab-0.9.dist-info/DESCRIPTION.rst
ayab-0.9.dist-info/LICENSE.txt
ayab-0.9.dist-info/METADATA
ayab-0.9.dist-info/RECORD
ayab-0.9.dist-info/WHEEL
ayab-0.9.dist-info/metadata.json
ayab-0.9.dist-info/top_level.txt
