Metadata-Version: 2.0
Name: ayab
Version: 0.9
Summary: GUI for Machine assisted Knitting. Reference implementation for AYAB.
Home-page: http://ayab-knitting.com/
Author: Christian Obersteiner, Andreas Müller, Sebastian Oliva, Christian Gerbrandt
Author-email: info@ayab-knitting.com
License: GPLv3+
Platform: any
Classifier: Programming Language :: Python
Classifier: Development Status :: 4 - Beta
Classifier: Natural Language :: English
Classifier: License :: OSI Approved :: GNU General Public License v3 or later (GPLv3+)
Classifier: Intended Audience :: End Users/Desktop
Classifier: Operating System :: OS Independent
Requires-Dist: Pillow (==4.1.0)
Requires-Dist: Yapsy (==1.11.223)
Requires-Dist: fysom (==2.1.3)
Requires-Dist: pyserial (==3.3)
